weatherbot/__init__.py
weatherbot/__main__.py
weatherbot/ai_enhancer.py
weatherbot/ai_map_analyzer.py
weatherbot/ai_web_search.py
weatherbot/alert_levels.py
weatherbot/alerting.py
weatherbot/atcf_client.py
weatherbot/cache.py
weatherbot/cli.py
weatherbot/config.py
weatherbot/coverage_validator.py
weatherbot/enhanced_cone_analyzer.py
weatherbot/geometry.py
weatherbot/logging_setup.py
weatherbot/nhc.py
weatherbot/nhc_current_storms.py
weatherbot/nhc_storm_tracker.py
weatherbot/nws.py
weatherbot/py.typed
weatherbot/reports.py
weatherbot/state.py
weatherbot/data/__init__.py
weatherbot/data/default_area.geojson
weatherbot/icons/README_ICON.md
weatherbot/icons/__init__.py
weatherbot/notifiers/__init__.py
weatherbot/notifiers/toast.py
weatherbot/notifiers/weather_map.py
weatherbot-1.0.0.dist-info/licenses/LICENSE
weatherbot-1.0.0.dist-info/METADATA
weatherbot-1.0.0.dist-info/WHEEL
weatherbot-1.0.0.dist-info/entry_points.txt
weatherbot-1.0.0.dist-info/top_level.txt
weatherbot-1.0.0.dist-info/RECORD
