Metadata-Version: 2.4
Name: weatherbot
Version: 1.0.0
Summary: Local hurricane alert system with NHC cone tracking, NWS alerts, and AI-powered threat analysis
Home-page: https://github.com/nathanramoscfa/weatherbot
Author: Weather Alert System
Author-email: Nathan Ramos <nathanramoscfa@gmail.com>
Maintainer-email: Nathan Ramos <nathanramoscfa@gmail.com>
License-Expression: MIT
Project-URL: Homepage, https://github.com/nathanramoscfa/weatherbot
Project-URL: Repository, https://github.com/nathanramoscfa/weatherbot.git
Project-URL: Documentation, https://github.com/nathanramoscfa/weatherbot/blob/master/README.md
Project-URL: Bug Tracker, https://github.com/nathanramoscfa/weatherbot/issues
Project-URL: Changelog, https://github.com/nathanramoscfa/weatherbot/blob/master/CHANGELOG.md
Keywords: weather,hurricane,alerts,notifications,NHC,NWS,weatherbot,AI,NOAA,tropical-storms,emergency-alerts
Classifier: Development Status :: 5 - Production/Stable
Classifier: Intended Audience :: End Users/Desktop
Classifier: Intended Audience :: Science/Research
Classifier: Operating System :: Microsoft :: Windows
Classifier: Operating System :: POSIX :: Linux
Classifier: Operating System :: MacOS
Classifier: Programming Language :: Python :: 3
Classifier: Programming Language :: Python :: 3.11
Classifier: Programming Language :: Python :: 3.12
Classifier: Topic :: Communications
Classifier: Topic :: Scientific/Engineering :: Atmospheric Science
Classifier: Topic :: Home Automation
Classifier: Topic :: Internet :: WWW/HTTP :: Dynamic Content
Classifier: Environment :: Console
Classifier: Natural Language :: English
Requires-Python: >=3.11
License-File: LICENSE
Requires-Dist: typer>=0.9.0
Requires-Dist: pydantic>=2.0.0
Requires-Dist: pydantic-settings>=2.0.0
Requires-Dist: requests>=2.31.0
Requires-Dist: shapely>=2.0.0
Requires-Dist: python-dotenv>=1.0.0
Requires-Dist: tenacity>=8.2.0
Requires-Dist: win11toast>=0.34
Requires-Dist: rich>=13.0.0
Requires-Dist: folium>=0.15.0
Requires-Dist: pillow>=10.0.0
Requires-Dist: matplotlib>=3.7.0
Requires-Dist: tkintermapview>=1.29
Requires-Dist: openai>=1.0.0
Requires-Dist: pandas>=2.0.0
Requires-Dist: beautifulsoup4>=4.12.0
Provides-Extra: dev
Requires-Dist: pytest>=7.4.0; extra == "dev"
Requires-Dist: pytest-cov>=4.0.0; extra == "dev"
Requires-Dist: black>=23.0.0; extra == "dev"
Requires-Dist: ruff>=0.1.0; extra == "dev"
Requires-Dist: pre-commit>=3.4.0; extra == "dev"
Requires-Dist: mypy>=1.5.0; extra == "dev"
Requires-Dist: bandit>=1.7.0; extra == "dev"
Requires-Dist: safety>=2.0.0; extra == "dev"
Requires-Dist: types-requests>=2.31.0; extra == "dev"
Requires-Dist: types-shapely>=2.0.0; extra == "dev"
Dynamic: license-file
